gnrparser/__init__.py
gnrparser/parser.py
gnrparser-1.0.0.dist-info/licenses/LICENSE
gnrparser-1.0.0.dist-info/METADATA
gnrparser-1.0.0.dist-info/WHEEL
gnrparser-1.0.0.dist-info/top_level.txt
gnrparser-1.0.0.dist-info/RECORD
