Metadata-Version: 2.4
Name: gnrparser
Version: 1.0.0
Summary: Library for parsing .gnr game notation files
Author: BesBobowyy
License: MIT License
Project-URL: Homepage, https://github.com/BesBobowyy/gnrparser
Requires-Python: >=3.6
License-File: LICENSE
Dynamic: license-file
Dynamic: requires-python
